pyFBS/IO.py
pyFBS/MCK.py
pyFBS/OSI.py
pyFBS/SEMM.py
pyFBS/SVT.py
pyFBS/VPT.py
pyFBS/__init__.py
pyFBS/app_stability.py
pyFBS/display.py
pyFBS/modal_id.py
pyFBS/utility.py
pyfbs-0.3.3.dist-info/licenses/AUTHORS.rst
pyfbs-0.3.3.dist-info/licenses/LICENSE
pyfbs-0.3.3.dist-info/METADATA
pyfbs-0.3.3.dist-info/WHEEL
pyfbs-0.3.3.dist-info/top_level.txt
pyfbs-0.3.3.dist-info/RECORD
