Metadata-Version: 2.4
Name: pyFBS
Version: 0.3.3
Summary: pyFBS: A Python package for Frequency Based Substructuring and Transfer Path Analysis
Author-email: "Tomaž Bregar, Ahmed El Mahmoudi, Miha Kodrič, Domen Ocepek, Francesco Trainotti, Miha Pogačar, Mert Göldeli, Tim Vrtač, Jure Korbar, Oliver Zobel" <info.pyfbs@gmail.com>
License-Expression: MIT
Project-URL: Homepage, https://pyfbs.readthedocs.io/en/master/intro.html
Requires-Python: >=3.11
License-File: LICENSE
License-File: AUTHORS.rst
Requires-Dist: numpy
Requires-Dist: ansys-mapdl-reader
Requires-Dist: ansys-dpf-core
Requires-Dist: ansys-dpf-post
Requires-Dist: pyuff
Requires-Dist: pyvista
Requires-Dist: pyvistaqt
Requires-Dist: pandas
Requires-Dist: scipy
Requires-Dist: tqdm
Requires-Dist: keyboard
Requires-Dist: requests
Requires-Dist: openpyxl
Requires-Dist: pyts
Requires-Dist: altair
Requires-Dist: matplotlib
Requires-Dist: h5py
Requires-Dist: PyQt5
Requires-Dist: imageio
Requires-Dist: polyrat
Provides-Extra: dev
Requires-Dist: pytest; extra == "dev"
Requires-Dist: pytest-cov; extra == "dev"
Requires-Dist: pytest-qt; extra == "dev"
Requires-Dist: codecov; extra == "dev"
Requires-Dist: coverage; extra == "dev"
Requires-Dist: qtpy; extra == "dev"
Requires-Dist: scooby; extra == "dev"
Requires-Dist: nbconvert; extra == "dev"
Requires-Dist: jupyterlab; extra == "dev"
Dynamic: license-file
